<?xml version='1.0' encoding='UTF-8'?>
<!DOCTYPE Application PUBLIC "sailpoint.dtd" "sailpoint.dtd">
<Application authoritative="true" connector="sailpoint.connector.DelimitedFileConnector" featuresString="DIRECT_PERMISSIONS, NO_RANDOM_ACCESS, DISCOVER_SCHEMA" icon="enterpriseIcon" name="HR Application" profileClass="" type="DelimitedFile">
  <Attributes>
    <Map>
      <entry key="acctAggregationEnd">
        <value>
          <Date>1545421450213</Date>
        </value>
      </entry>
      <entry key="acctAggregationStart">
        <value>
          <Date>1545421446880</Date>
        </value>
      </entry>
      <entry key="compositeDefinition"/>
      <entry key="delimiter" value=","/>
      <entry key="file" value="C:\Users\Rupak\Desktop\SAILPOINT_START_STOP\SAIL_POINT_RUPAK_WORKS\employee.txt"/>
      <entry key="filetransport" value="local"/>
      <entry key="filterEmptyRecords">
        <value>
          <Boolean>true</Boolean>
        </value>
      </entry>
      <entry key="group.filetransport" value="local"/>
      <entry key="group.filterEmptyRecords">
        <value>
          <Boolean>true</Boolean>
        </value>
      </entry>
      <entry key="group.partitionMode" value="auto"/>
      <entry key="hasHeader">
        <value>
          <Boolean>true</Boolean>
        </value>
      </entry>
      <entry key="isCaseInsensitiveMerge">
        <value>
          <Boolean/>
        </value>
      </entry>
      <entry key="isSortedByIndexColumn">
        <value>
          <Boolean/>
        </value>
      </entry>
      <entry key="managerCorrelationFilter">
        <value>
          <Filter operation="EQ"/>
        </value>
      </entry>
      <entry key="mergeRows">
        <value>
          <Boolean/>
        </value>
      </entry>
      <entry key="nativeChangeDetectionAttributeScope" value="entitlements"/>
      <entry key="nativeChangeDetectionAttributes"/>
      <entry key="nativeChangeDetectionEnabled">
        <value>
          <Boolean/>
        </value>
      </entry>
      <entry key="nativeChangeDetectionOperations"/>
      <entry key="parseType" value="delimited"/>
      <entry key="partitionMode" value="auto"/>
      <entry key="stopIfLineHasWrongColumnLength">
        <value>
          <Boolean/>
        </value>
      </entry>
      <entry key="sysDescriptions">
        <value>
          <Map>
            <entry key="en_US"/>
          </Map>
        </value>
      </entry>
      <entry key="templateApplication" value="DelimitedFile Template"/>
      <entry key="transportUserPassword" value="1:p+qvPBo4Rig8PYlNWbr3Zg=="/>
    </Map>
  </Attributes>
  <CreationRule>
    <Reference class="sailpoint.object.Rule" name="D Experts Creation Rule"/>
  </CreationRule>
  <CustomizationRule>
    <Reference class="sailpoint.object.Rule" name="D Experts HR Customizatrion Rule"/>
  </CustomizationRule>
  <ManagerCorrelationRule>
    <Reference class="sailpoint.object.Rule" name="Manager coorelation rule"/>
  </ManagerCorrelationRule>
  <Owner>
    <Reference class="sailpoint.object.Identity" name="spadmin"/>
  </Owner>
  <Schemas>
    <Schema displayAttribute="username" identityAttribute="id" instanceAttribute="" nativeObjectType="account" objectType="account" permissionsRemediationModificationType="None">
      <AttributeDefinition name="id" type="string"/>
      <AttributeDefinition name="username" type="string"/>
      <AttributeDefinition name="firstname" type="string"/>
      <AttributeDefinition name="lastname" type="string"/>
      <AttributeDefinition name="gender" type="string"/>
      <AttributeDefinition name="email" type="string"/>
      <AttributeDefinition name="department" type="string"/>
      <AttributeDefinition name="managerid" type="string"/>
      <AttributeDefinition name="status" type="int"/>
    </Schema>
  </Schemas>
  <ApplicationScorecard/>
</Application>